geocontour/__init__.py
geocontour/check.py
geocontour/contourtrace.py
geocontour/contourutil.py
geocontour/geocontour.py
geocontour/grid.py
geocontour/masksearch.py
geocontour/maskutil.py
geocontour/output.py
geocontour/data/MissBasin_boundary.npz
geocontour/data/box_boundary.npz
geocontour/data/generic_boundary.npz
geocontour/data/test_case_boundary.npz
geocontour/examples/__init__.py
geocontour/tests/__init__.py
geocontour/tests/timing.py
geocontour-1.3.1.dist-info/LICENSE.txt
geocontour-1.3.1.dist-info/METADATA
geocontour-1.3.1.dist-info/WHEEL
geocontour-1.3.1.dist-info/top_level.txt
geocontour-1.3.1.dist-info/RECORD
