Metadata-Version: 2.1
Name: geocontour
Version: 1.3.1
Summary: Utilities for masking, contour tracing, and geocontour construction with gridded geographic data
Home-page: https://github.com/benkrichman/geocontour
Author: Benjamin Krichman
Author-email: benkrichman@gmail.com
License: MIT
Classifier: Programming Language :: Python :: 3
Classifier: License :: OSI Approved :: MIT License
Classifier: Intended Audience :: Science/Research
Classifier: Topic :: Scientific/Engineering
Classifier: Topic :: Scientific/Engineering :: Atmospheric Science
Classifier: Topic :: Scientific/Engineering :: Hydrology
Classifier: Topic :: Scientific/Engineering :: Visualization
License-File: LICENSE.txt
Requires-Dist: numpy
Requires-Dist: scipy
Requires-Dist: matplotlib
Requires-Dist: shapely
Requires-Dist: datascale
